sshtop/__main__.py
sshtop/commands.py
sshtop/monitor.py
sshtop/result.py
sshtop/ssh.py
sshtop/utils.py
sshtop-2.0.1.dist-info/entry_points.txt
sshtop-2.0.1.dist-info/LICENSE
sshtop-2.0.1.dist-info/WHEEL
sshtop-2.0.1.dist-info/METADATA
sshtop-2.0.1.dist-info/RECORD
