Metadata-Version: 2.1
Name: sshtop
Version: 2.0.1
Summary: Remote server monitoring tool over SSH
Home-page: https://github.com/exler/sshtop
License: MIT
Author: Kamil Marut
Author-email: kamil@kamilmarut.com
Requires-Python: >=3.6.2,<4.0.0
Classifier: Environment :: Console
Classifier: License :: OSI Approved :: MIT License
Classifier: Operating System :: OS Independent
Classifier: Programming Language :: Python :: 3
Classifier: Programming Language :: Python :: 3.10
Classifier: Programming Language :: Python :: 3.7
Classifier: Programming Language :: Python :: 3.8
Classifier: Programming Language :: Python :: 3.9
Classifier: Topic :: System :: Monitoring
Requires-Dist: colorama (>=0.4.4,<0.5.0)
Requires-Dist: paramiko (>=2.8.1,<3.0.0)
Project-URL: Bug Tracker, https://github.com/exler/sshtop/issues
Project-URL: Repository, https://github.com/exler/sshtop
